irt/__init__.py
irt/common/helper.py
irt/common/logger.py
irt/data/dataset.py
irt/data/pykeen.py
irt/data/pytorch.py
irt/graph/graph.py
irt/graph/loader.py
irt/graph/split.py
irt/text/__init__.py
irt/text/loader.py
irt/text/selector.py
irt_data-1.2.1.dist-info/LICENSE
irt_data-1.2.1.dist-info/METADATA
irt_data-1.2.1.dist-info/WHEEL
irt_data-1.2.1.dist-info/top_level.txt
irt_data-1.2.1.dist-info/RECORD
