Metadata-Version: 2.1
Name: irt-data
Version: 1.2.1
Summary: Inductive Reasoning with Text - Benchmarks
Author: Felix Hamann
Author-email: felix@hamann.xyz
License: MIT
Platform: UNKNOWN
License-File: LICENSE
Requires-Dist: pyyaml (==5.*)
Requires-Dist: networkx (==2.*)
Requires-Dist: gitpython (==3.*)
Requires-Dist: tqdm
Requires-Dist: jupyter
Requires-Dist: tabulate
Requires-Dist: matplotlib
